{"py/object": "rasa.core.featurizers.tracker_featurizers.IntentMaxHistoryTrackerFeaturizer", "state_featurizer": {"py/object": "rasa.core.featurizers.single_state_featurizer.IntentTokenizerSingleStateFeaturizer", "_default_feature_states": {"intent": {"Mservices": 0, "affirm": 1, "back": 2, "bot_challenge": 3, "contact": 4, "define": 5, "deny": 6, "email": 7, "goodbye": 8, "greet": 9, "innovations": 10, "iso": 11, "leb_loc": 12, "locations": 13, "mood_great": 14, "mood_unhappy": 15, "nlu_fallback": 16, "out_of_scope": 17, "partners": 18, "phone": 19, "restart": 20, "session_start": 21, "size": 22, "solutions": 23, "specialties": 24, "thanks": 25, "values": 26, "website": 27, "year": 28}, "action_name": {"action_listen": 0, "action_restart": 1, "action_session_start": 2, "action_default_fallback": 3, "action_deactivate_loop": 4, "action_revert_fallback_events": 5, "action_default_ask_affirmation": 6, "action_default_ask_rephrase": 7, "action_two_stage_fallback": 8, "action_unlikely_intent": 9, "action_back": 10, "...": 11, "action_extract_slots": 12, "utter_Mservices": 13, "utter_cheer_up": 14, "utter_contact": 15, "utter_define": 16, "utter_did_that_help": 17, "utter_email": 18, "utter_goodbye": 19, "utter_greet": 20, "utter_happy": 21, "utter_iamabot": 22, "utter_innovations": 23, "utter_iso": 24, "utter_leb_loc": 25, "utter_locations": 26, "utter_partners": 27, "utter_phone": 28, "utter_size": 29, "utter_solutions": 30, "utter_specialties": 31, "utter_thanks": 32, "utter_values": 33, "utter_website": 34, "utter_year": 35}, "entities": {}, "slots": {}, "active_loop": {}}, "action_texts": [], "entity_tag_specs": []}, "max_history": 5, "remove_duplicates": true}